MANIFEST.in
README.md
setup.py
jsonbind/README.md
jsonbind/__init__.py
jsonbind/basic_functions.py
jsonbind/decorators.py
jsonbind/license.txt
jsonbind/setup.cfg
jsonbind.egg-info/PKG-INFO
jsonbind.egg-info/SOURCES.txt
jsonbind.egg-info/dependency_links.txt
jsonbind.egg-info/not-zip-safe
jsonbind.egg-info/requires.txt
jsonbind.egg-info/top_level.txt
jsonbind/__pycache__/__init__.cpython-312.pyc
jsonbind/__pycache__/basic_functions.cpython-312.pyc
jsonbind/__pycache__/bytes.cpython-312.pyc
jsonbind/__pycache__/class_binding.cpython-312.pyc
jsonbind/__pycache__/datetime.cpython-312.pyc
jsonbind/__pycache__/decorators.cpython-312.pyc
jsonbind/__pycache__/enum.cpython-312.pyc
jsonbind/__pycache__/list.cpython-312.pyc
jsonbind/__pycache__/object.cpython-312.pyc
jsonbind/__pycache__/search.cpython-312.pyc
jsonbind/__pycache__/serializable.cpython-312.pyc
jsonbind/__pycache__/serialization.cpython-312.pyc
jsonbind/__pycache__/tuple.cpython-312.pyc
jsonbind/__pycache__/type_binding.cpython-312.pyc
jsonbind/addons/__init__.py
jsonbind/addons/numpy.py
jsonbind/addons/pandas.py
jsonbind/addons/__pycache__/__init__.cpython-312.pyc
jsonbind/addons/__pycache__/numpy.cpython-312.pyc
jsonbind/addons/__pycache__/pandas.cpython-312.pyc
jsonbind/bindings/__init__.py
jsonbind/bindings/bytes.py
jsonbind/bindings/class_binding.py
jsonbind/bindings/datetime.py
jsonbind/bindings/enum.py
jsonbind/bindings/set.py
jsonbind/bindings/tuple.py
jsonbind/bindings/__pycache__/__init__.cpython-312.pyc
jsonbind/bindings/__pycache__/bytes.cpython-312.pyc
jsonbind/bindings/__pycache__/class_binding.cpython-312.pyc
jsonbind/bindings/__pycache__/datetime.cpython-312.pyc
jsonbind/bindings/__pycache__/enum.cpython-312.pyc
jsonbind/bindings/__pycache__/set.cpython-312.pyc
jsonbind/bindings/__pycache__/tuple.cpython-312.pyc
jsonbind/core/__init__.py
jsonbind/core/serialization.py
jsonbind/core/type_binding.py
jsonbind/core/__pycache__/__init__.cpython-312.pyc
jsonbind/core/__pycache__/serialization.cpython-312.pyc
jsonbind/core/__pycache__/type_binding.cpython-312.pyc
jsonbind/special/__init__.py
jsonbind/special/list.py
jsonbind/special/object.py
jsonbind/special/serializable.py
