Metadata-Version: 2.1
Name: jsonbind
Version: 0.0.18
Summary: a better json library
Home-page: https://github.com/germanespinosa/jsonbind
Author: german espinosa
Author-email: germanespinosa@gmail.com
License: MIT
Requires-Dist: requests
